maeapi/__init__.py
maeapi/_version.py
maeapi/constants.py
maeapi/helpers.py
maeapi/maeapi.py
maeapi/utils.py
maeapi/mixins/__init__.py
maeapi/mixins/banking.py
maeapi/mixins/transaction.py
maeapi/parsers/__init__.py
maeapi/parsers/banking.py
maeapi/parsers/transaction.py
maeapi-0.2.dist-info/METADATA
maeapi-0.2.dist-info/WHEEL
maeapi-0.2.dist-info/top_level.txt
maeapi-0.2.dist-info/RECORD
