Metadata-Version: 2.1
Name: maeapi
Version: 0.2
Summary: Unofficial API for MAE
Home-page: https://github.com/liej6799/maeapi
Author: liej6799
Author-email: 
License: MIT
Platform: UNKNOWN
Requires-Python: >=3.6
Requires-Dist: requests (>=2.22)
